{
  "name": "David Schliesing",
  "party": "DIE LINKE",
  "slug": "david-schliesing",
  "academicTitle": null,
  "speeches": 7,
  "wortbeitraege": 2,
  "befragungResponses": 0,
  "totalWords": 3367,
  "avgWords": 374,
  "minWords": 254,
  "maxWords": 464,
  "rankings": {
    "speechRank": 277,
    "wordsRank": 325,
    "partySpeechRank": 33,
    "partyWordsRank": 32,
    "partySize": 63,
    "totalSpeakers": 609,
    "percentile": 54.5,
    "verbosityRank": 377,
    "verbosityTotal": 521,
    "partyVerbosityRank": 33,
    "longestSpeechRank": 548
  },
  "drama": {
    "interruptionsGiven": 0,
    "interruptionsReceived": 10,
    "interrupterRank": 251,
    "interruptedRank": 279
  },
  "words": {
    "topWords": [
      {
        "word": "deutschen",
        "count": 11
      },
      {
        "word": "weimer",
        "count": 11
      },
      {
        "word": "kultur",
        "count": 10
      },
      {
        "word": "menschen",
        "count": 8
      },
      {
        "word": "kunst",
        "count": 7
      },
      {
        "word": "haushalt",
        "count": 7
      },
      {
        "word": "kolonialismus",
        "count": 7
      },
      {
        "word": "beispiel",
        "count": 6
      },
      {
        "word": "verlage",
        "count": 6
      },
      {
        "word": "freiheit",
        "count": 5
      }
    ],
    "signatureWordsBundestag": [
      {
        "word": "weimer",
        "count": 11,
        "score": 44.1,
        "ratio": 54.1
      },
      {
        "word": "kolonialismus",
        "count": 7,
        "score": 40.5,
        "ratio": 326.9
      },
      {
        "word": "kultur",
        "count": 10,
        "score": 33.2,
        "ratio": 26.7
      },
      {
        "word": "kunst",
        "count": 7,
        "score": 31.6,
        "ratio": 90.2
      },
      {
        "word": "verlage",
        "count": 6,
        "score": 30.1,
        "ratio": 149.4
      }
    ],
    "signatureWordsParty": [
      {
        "word": "weimer",
        "count": 11,
        "score": 49.0,
        "ratio": 85.0
      },
      {
        "word": "kultur",
        "count": 10,
        "score": 36.8,
        "ratio": 38.6
      },
      {
        "word": "kolonialismus",
        "count": 7,
        "score": 36.4,
        "ratio": 180.2
      },
      {
        "word": "kunst",
        "count": 7,
        "score": 30.5,
        "ratio": 77.2
      },
      {
        "word": "deutschen",
        "count": 11,
        "score": 22.0,
        "ratio": 6.4
      }
    ],
    "signatureAdjectivesBundestag": [
      {
        "word": "sicher",
        "count": 3,
        "score": 4.2,
        "ratio": 3.0
      }
    ],
    "signatureAdjectivesParty": [
      {
        "word": "sicher",
        "count": 3,
        "score": 4.9,
        "ratio": 4.1
      }
    ]
  },
  "comparison": {
    "speakerAvgWords": 374,
    "partyAvgWords": 521,
    "parliamentAvgWords": 613,
    "vsParty": 0.72,
    "vsParliament": 0.61
  },
  "funFacts": [
    {
      "emoji": "🎤",
      "label": "Reden gehalten",
      "value": "7"
    },
    {
      "emoji": "📝",
      "label": "Wörter gesprochen",
      "value": "3.367"
    }
  ],
  "signatureQuiz": {
    "question": "Welches Wort nutzt David Schliesing häufiger als der Bundestag-Durchschnitt?",
    "options": [
      {
        "text": "Abstimmung",
        "isCorrect": false
      },
      {
        "text": "Freiheit",
        "isCorrect": false
      },
      {
        "text": "Energie",
        "isCorrect": false
      },
      {
        "text": "Weimer",
        "isCorrect": true
      }
    ],
    "explanation": "\"Weimer\" sagte David Schliesing 11× (54.1× häufiger als der Bundestag-Durchschnitt)."
  },
  "signatureAdjectiveQuiz": {
    "question": "Welches Adjektiv nutzt David Schliesing häufiger als der Bundestag-Durchschnitt?",
    "options": [
      {
        "text": "Gefährlich",
        "isCorrect": false
      },
      {
        "text": "Erfolgreich",
        "isCorrect": false
      },
      {
        "text": "Sicher",
        "isCorrect": true
      },
      {
        "text": "Notwendig",
        "isCorrect": false
      }
    ],
    "explanation": "\"Sicher\" sagte David Schliesing 3× (3.0× häufiger als der Bundestag-Durchschnitt)."
  },
  "spiritAnimal": {
    "emoji": "🐬",
    "name": "Delfin",
    "title": "Diplomatischer Redner",
    "reason": "Aktiv im Parlament, aber respektvoll ohne viele Zwischenrufe.",
    "id": "delfin",
    "alternatives": [
      {
        "emoji": "🐿️",
        "name": "Eichhörnchen",
        "title": "Themenhüter",
        "reason": "Du hast deine Spezialthemen, die du immer wieder einbringst.",
        "id": "eichhoernchen",
        "score": 0.935
      },
      {
        "emoji": "🦫",
        "name": "Biber",
        "title": "Konstruktiver Brückenbauer",
        "reason": "Du baust Brücken zwischen Positionen – kooperativ und lösungsorientiert.",
        "id": "biber",
        "score": 0.925
      }
    ]
  },
  "toneProfile": {
    "scores": {
      "affirmative": 58.8,
      "aggression": 4.8,
      "labeling": 14.3,
      "solution_focus": 75.0,
      "collaboration": 100.0,
      "demand_intensity": 13.0,
      "acknowledgment": 8.7,
      "authority": 75.0,
      "future_orientation": 86.8,
      "emotional_intensity": 54.5,
      "inclusivity": 32.0,
      "discriminatory": 0.0
    },
    "confidence": "sufficient",
    "sampleSize": {
      "speeches": 9,
      "words": 2229,
      "adjectives": 21,
      "verbs": 23
    }
  },
  "topics": {
    "scores": {
      "migration": 0.9,
      "klima": 0.0,
      "wirtschaft": 0.0,
      "soziales": 0.9,
      "sicherheit": 5.38,
      "gesundheit": 0.0,
      "europa": 2.69,
      "digital": 0.9,
      "bildung": 0.9,
      "finanzen": 5.38,
      "justiz": 2.24,
      "arbeit": 0.0,
      "mobilitaet": 0.0
    },
    "topTopics": [
      {
        "topic": "sicherheit",
        "score": 5.38,
        "rank": 1
      },
      {
        "topic": "finanzen",
        "score": 5.38,
        "rank": 2
      },
      {
        "topic": "europa",
        "score": 2.69,
        "rank": 3
      },
      {
        "topic": "justiz",
        "score": 2.24,
        "rank": 4
      },
      {
        "topic": "migration",
        "score": 0.9,
        "rank": 5
      }
    ],
    "topicWords": {
      "migration": [
        {
          "word": "integration",
          "count": 1
        },
        {
          "word": "grenze",
          "count": 1
        }
      ],
      "soziales": [
        {
          "word": "armut",
          "count": 1
        },
        {
          "word": "kinder",
          "count": 1
        }
      ],
      "sicherheit": [
        {
          "word": "verbrechen",
          "count": 5
        },
        {
          "word": "gewalt",
          "count": 2
        },
        {
          "word": "betrug",
          "count": 1
        },
        {
          "word": "geldwäsche",
          "count": 1
        },
        {
          "word": "mord",
          "count": 1
        }
      ],
      "europa": [
        {
          "word": "bündnis",
          "count": 2
        },
        {
          "word": "krieg",
          "count": 2
        },
        {
          "word": "putin",
          "count": 1
        },
        {
          "word": "frieden",
          "count": 1
        }
      ],
      "digital": [
        {
          "word": "digitalisierung",
          "count": 1
        },
        {
          "word": "plattform",
          "count": 1
        }
      ],
      "bildung": [
        {
          "word": "forschung",
          "count": 1
        },
        {
          "word": "kita",
          "count": 1
        }
      ],
      "finanzen": [
        {
          "word": "haushalt",
          "count": 7
        },
        {
          "word": "sondervermögen",
          "count": 2
        },
        {
          "word": "kosten",
          "count": 1
        },
        {
          "word": "etat",
          "count": 1
        },
        {
          "word": "steuerhinterziehung",
          "count": 1
        }
      ],
      "justiz": [
        {
          "word": "grundgesetz",
          "count": 2
        },
        {
          "word": "diskriminierung",
          "count": 1
        },
        {
          "word": "straftaten",
          "count": 1
        },
        {
          "word": "beschluss",
          "count": 1
        }
      ]
    }
  }
}