{
  "name": "Susanne Hierl",
  "party": "CDU/CSU",
  "slug": "susanne-hierl",
  "academicTitle": null,
  "speeches": 6,
  "wortbeitraege": 2,
  "befragungResponses": 0,
  "totalWords": 4065,
  "avgWords": 508,
  "minWords": 103,
  "maxWords": 893,
  "rankings": {
    "speechRank": 293,
    "wordsRank": 250,
    "partySpeechRank": 72,
    "partyWordsRank": 74,
    "partySize": 203,
    "totalSpeakers": 609,
    "percentile": 51.9,
    "verbosityRank": 153,
    "verbosityTotal": 521,
    "partyVerbosityRank": 56,
    "longestSpeechRank": 108
  },
  "drama": {
    "interruptionsGiven": 0,
    "interruptionsReceived": 5,
    "interrupterRank": null,
    "interruptedRank": 398
  },
  "words": {
    "topWords": [
      {
        "word": "justiz",
        "count": 27
      },
      {
        "word": "haushalt",
        "count": 18
      },
      {
        "word": "verbraucherschutz",
        "count": 13
      },
      {
        "word": "vertrauen",
        "count": 13
      },
      {
        "word": "verfahren",
        "count": 13
      },
      {
        "word": "rechtsstaat",
        "count": 11
      },
      {
        "word": "setzen",
        "count": 10
      },
      {
        "word": "gesetzentwurf",
        "count": 10
      },
      {
        "word": "frauen",
        "count": 9
      },
      {
        "word": "bürgerinnen",
        "count": 8
      }
    ],
    "signatureWordsBundestag": [
      {
        "word": "justiz",
        "count": 27,
        "score": 107.4,
        "ratio": 52.4
      },
      {
        "word": "verbraucherschutz",
        "count": 13,
        "score": 54.3,
        "ratio": 64.0
      },
      {
        "word": "verfahren",
        "count": 13,
        "score": 33.7,
        "ratio": 12.3
      },
      {
        "word": "haushalt",
        "count": 18,
        "score": 31.2,
        "ratio": 4.7
      },
      {
        "word": "rechtsstaat",
        "count": 11,
        "score": 31.0,
        "ratio": 15.8
      }
    ],
    "signatureWordsParty": [
      {
        "word": "justiz",
        "count": 27,
        "score": 110.1,
        "ratio": 58.1
      },
      {
        "word": "verbraucherschutz",
        "count": 13,
        "score": 55.4,
        "ratio": 70.0
      },
      {
        "word": "verfahren",
        "count": 13,
        "score": 30.4,
        "ratio": 9.4
      },
      {
        "word": "haushalt",
        "count": 18,
        "score": 30.1,
        "ratio": 4.3
      },
      {
        "word": "rechtsstaat",
        "count": 11,
        "score": 30.0,
        "ratio": 14.2
      }
    ],
    "signatureAdjectivesBundestag": [],
    "signatureAdjectivesParty": []
  },
  "comparison": {
    "speakerAvgWords": 508,
    "partyAvgWords": 688,
    "parliamentAvgWords": 613,
    "vsParty": 0.74,
    "vsParliament": 0.83
  },
  "funFacts": [
    {
      "emoji": "🎤",
      "label": "Reden gehalten",
      "value": "6"
    },
    {
      "emoji": "📝",
      "label": "Wörter gesprochen",
      "value": "4.065"
    }
  ],
  "signatureQuiz": {
    "question": "Welches Wort nutzt Susanne Hierl häufiger als der Bundestag-Durchschnitt?",
    "options": [
      {
        "text": "Justiz",
        "isCorrect": true
      },
      {
        "text": "Kanzler",
        "isCorrect": false
      },
      {
        "text": "Familie",
        "isCorrect": false
      },
      {
        "text": "Bildung",
        "isCorrect": false
      }
    ],
    "explanation": "\"Justiz\" sagte Susanne Hierl 27× (52.4× häufiger als der Bundestag-Durchschnitt)."
  },
  "signatureAdjectiveQuiz": null,
  "spiritAnimal": {
    "emoji": "🐝",
    "name": "Biene",
    "title": "Fleißige Abgeordnete",
    "reason": "Zuverlässig und engagiert – ein wichtiger Teil des Parlaments.",
    "id": "biene",
    "alternatives": [
      {
        "emoji": "🐿️",
        "name": "Eichhörnchen",
        "title": "Themenhüterin",
        "reason": "Du hast deine Spezialthemen, die du immer wieder einbringst.",
        "id": "eichhoernchen",
        "score": 0.963
      },
      {
        "emoji": "🦦",
        "name": "Otter",
        "title": "Positive Teamplayerin",
        "reason": "Du bringst gute Stimmung und konstruktive Beiträge ins Plenum.",
        "id": "otter",
        "score": 0.875
      }
    ]
  },
  "toneProfile": {
    "scores": {
      "affirmative": 100.0,
      "aggression": 0.0,
      "labeling": 0.0,
      "solution_focus": 91.7,
      "collaboration": 66.7,
      "demand_intensity": 8.7,
      "acknowledgment": 6.5,
      "authority": 68.8,
      "future_orientation": 91.9,
      "emotional_intensity": 33.3,
      "inclusivity": 60.0,
      "discriminatory": 0.0
    },
    "confidence": "sufficient",
    "sampleSize": {
      "speeches": 8,
      "words": 2600,
      "adjectives": 9,
      "verbs": 46
    }
  },
  "topics": {
    "scores": {
      "migration": 0.0,
      "klima": 0.0,
      "wirtschaft": 4.62,
      "soziales": 7.69,
      "sicherheit": 6.15,
      "gesundheit": 0.38,
      "europa": 0.38,
      "digital": 4.23,
      "bildung": 0.38,
      "finanzen": 9.23,
      "justiz": 16.54,
      "arbeit": 0.38,
      "mobilitaet": 0.38
    },
    "topTopics": [
      {
        "topic": "justiz",
        "score": 16.54,
        "rank": 1
      },
      {
        "topic": "finanzen",
        "score": 9.23,
        "rank": 2
      },
      {
        "topic": "soziales",
        "score": 7.69,
        "rank": 3
      },
      {
        "topic": "sicherheit",
        "score": 6.15,
        "rank": 4
      },
      {
        "topic": "wirtschaft",
        "score": 4.62,
        "rank": 5
      }
    ],
    "topicWords": {
      "wirtschaft": [
        {
          "word": "unternehmen",
          "count": 5
        },
        {
          "word": "wettbewerb",
          "count": 2
        },
        {
          "word": "industrie",
          "count": 2
        },
        {
          "word": "wirtschaftspolitik",
          "count": 1
        },
        {
          "word": "markt",
          "count": 1
        }
      ],
      "soziales": [
        {
          "word": "kinder",
          "count": 7
        },
        {
          "word": "mietpreisbremse",
          "count": 6
        },
        {
          "word": "mieten",
          "count": 5
        },
        {
          "word": "wohnungsmarkt",
          "count": 1
        },
        {
          "word": "wohnungen",
          "count": 1
        }
      ],
      "sicherheit": [
        {
          "word": "gewalt",
          "count": 6
        },
        {
          "word": "täter",
          "count": 5
        },
        {
          "word": "angriff",
          "count": 2
        },
        {
          "word": "terrorismus",
          "count": 1
        },
        {
          "word": "kriminalität",
          "count": 1
        }
      ],
      "gesundheit": [
        {
          "word": "prävention",
          "count": 1
        }
      ],
      "europa": [
        {
          "word": "partnerschaft",
          "count": 1
        }
      ],
      "digital": [
        {
          "word": "digitalisierung",
          "count": 5
        },
        {
          "word": "digital",
          "count": 2
        },
        {
          "word": "software",
          "count": 1
        },
        {
          "word": "daten",
          "count": 1
        },
        {
          "word": "cloud",
          "count": 1
        }
      ],
      "bildung": [
        {
          "word": "universität",
          "count": 1
        }
      ],
      "finanzen": [
        {
          "word": "haushalt",
          "count": 18
        },
        {
          "word": "kosten",
          "count": 2
        },
        {
          "word": "investitionen",
          "count": 2
        },
        {
          "word": "bundeshaushalt",
          "count": 2
        }
      ],
      "justiz": [
        {
          "word": "verbraucherschutz",
          "count": 13
        },
        {
          "word": "rechtsstaat",
          "count": 11
        },
        {
          "word": "bundesverfassungsgericht",
          "count": 3
        },
        {
          "word": "gerichte",
          "count": 3
        },
        {
          "word": "strafverfolgung",
          "count": 2
        }
      ],
      "arbeit": [
        {
          "word": "arbeitsplätze",
          "count": 1
        }
      ],
      "mobilitaet": [
        {
          "word": "infrastruktur",
          "count": 1
        }
      ]
    }
  }
}